r2pb/__init__.py
r2pb/cli.py
r2pb/converter.py
r2pb/fetcher.py
r2pb/generator.py
r2pb/mapper.py
r2pb/parser.py
r2pb/templates/msg.proto.j2
r2pb-0.1.2.dist-info/licenses/LICENSE
r2pb-0.1.2.dist-info/METADATA
r2pb-0.1.2.dist-info/WHEEL
r2pb-0.1.2.dist-info/entry_points.txt
r2pb-0.1.2.dist-info/top_level.txt
r2pb-0.1.2.dist-info/RECORD
