Metadata-Version: 2.4
Name: r2pb
Version: 0.1.2
Summary: A simple tool to convert ROS .msg files to Protobuf .proto files.
Author-email: Mark <hzypp1995@gmail.com>
Project-URL: Homepage, https://github.com/tz-bb/r2pb
Project-URL: Bug Tracker, https://github.com/tz-bb/r2pb/issues
Classifier: Programming Language :: Python :: 3
Classifier: License :: OSI Approved :: GNU Affero General Public License v3 or later (AGPLv3+)
Classifier: Operating System :: OS Independent
Requires-Python: >=3.8
License-File: LICENSE
Requires-Dist: jinja2
Requires-Dist: requests
Requires-Dist: rosdistro
Requires-Dist: pyyaml
Requires-Dist: GitPython
Provides-Extra: dev
Requires-Dist: pytest; extra == "dev"
Requires-Dist: black; extra == "dev"
Requires-Dist: ruff; extra == "dev"
Dynamic: license-file
